MANIFEST.in
setup.py
asciipr0n/__init__.py
asciipr0n.egg-info/PKG-INFO
asciipr0n.egg-info/SOURCES.txt
asciipr0n.egg-info/dependency_links.txt
asciipr0n.egg-info/top_level.txt
asciipr0n/data/pinup01.txt
asciipr0n/data/pinup02.txt
asciipr0n/data/pinup03.txt
asciipr0n/data/pinup04.txt
asciipr0n/data/pinup05.txt
asciipr0n/data/pinup06.txt
asciipr0n/data/pinup07.txt
asciipr0n/data/pinup08.txt
asciipr0n/data/pinup09.txt
asciipr0n/data/pinup10.txt
asciipr0n/data/pinup11.txt
asciipr0n/data/pinup12.txt
asciipr0n/data/pinup13.txt
asciipr0n/data/pinup14.txt
asciipr0n/data/pinup15.txt
asciipr0n/data/pinup16.txt
asciipr0n/data/pinup17.txt
asciipr0n/data/pinup18.txt
asciipr0n/data/pinup19.txt
asciipr0n/data/pinup20.txt
asciipr0n/data/pinup21.txt
asciipr0n/data/pinup22.txt
asciipr0n/data/pinup23.txt
asciipr0n/data/pinup24.txt
asciipr0n/data/pinup25.txt
asciipr0n/data/pinup26.txt
asciipr0n/data/pinup27.txt
asciipr0n/data/pinup28.txt
asciipr0n/data/pinup29.txt
asciipr0n/data/pinup30.txt
asciipr0n/data/pinup31.txt
asciipr0n/data/pinup32.txt
asciipr0n/data/pinup33.txt
asciipr0n/data/pinup34.txt
asciipr0n/data/pinup35.txt
asciipr0n/data/pinup36.txt
asciipr0n/data/pinup37.txt
asciipr0n/data/pinup38.txt
asciipr0n/data/pinup39.txt
asciipr0n/data/pinup40.txt
asciipr0n/data/pinup41.txt
asciipr0n/data/pinup42.txt
asciipr0n/data/pinup43.txt
asciipr0n/data/pinup44.txt
asciipr0n/data/pinup45.txt
asciipr0n/data/pinup46.txt
asciipr0n/data/pinup47.txt
asciipr0n/data/pinup48.txt