Metadata-Version: 1.1
Name: asciipr0n
Version: 1.0.2
Summary: Display NSFW images in your logfiles
Home-page: UNKNOWN
Author: Rob Britton
Author-email: rob@robbritton.com
License: UNKNOWN
Platform: UNKNOWN
Classifier: Programming Language :: Python
Classifier: License :: OSI Approved :: Apache Software License
Classifier: Development Status :: 3 - Alpha
Classifier: Intended Audience :: Developers
Classifier: Topic :: System :: Logging
